climaf/__init__.py
climaf/anynetcdf.py
climaf/api.py
climaf/cache.py
climaf/classes.py
climaf/cmacro.py
climaf/dataloc.py
climaf/driver.py
climaf/easyCMIP_functions.py
climaf/functions.py
climaf/html.py
climaf/netcdfbasics.py
climaf/operators.py
climaf/operators_derive.py
climaf/operators_scripts.py
climaf/period.py
climaf/standard_operators.py
climaf/utils.py
climaf/derived_variables/__init__.py
climaf/derived_variables/atmosphere_derived_variables.py
climaf/derived_variables/cnrm_derived_variables.py
climaf/derived_variables/ipsl_derived_variables.py
climaf/derived_variables/ocean_derived_variables.py
climaf/plot/__init__.py
climaf/plot/atmos_plot_params.py
climaf/plot/atmos_plot_params_CNRM.py
climaf/plot/atmos_plot_params_IPSL.py
climaf/plot/land_plot_params.py
climaf/plot/land_plot_params_CNRM.py
climaf/plot/land_plot_params_IPSL.py
climaf/plot/ocean_plot_params.py
climaf/plot/ocean_plot_params_CNRM.py
climaf/plot/ocean_plot_params_IPSL.py
climaf/plot/plot_params.py
climaf/plot/varlongname.py
climaf/projects/__init__.py
climaf/projects/cami.py
climaf/projects/ceres.py
climaf/projects/cmip3.py
climaf/projects/cmip5.py
climaf/projects/cmip6.py
climaf/projects/cmip6cerfacs.py
climaf/projects/cordex.py
climaf/projects/cruts3.py
climaf/projects/em.py
climaf/projects/emn36.py
climaf/projects/eobs.py
climaf/projects/erai.py
climaf/projects/erai_land.py
climaf/projects/example.py
climaf/projects/file.py
climaf/projects/gpcc.py
climaf/projects/gpcp.py
climaf/projects/igcm_cmip6.py
climaf/projects/igcm_out.py
climaf/projects/nemo.py
climaf/projects/obs4mips.py
climaf/projects/ocmip5.py
climaf/projects/ref_climatos_and_ts.py
climaf/projects/ref_era5cerfacs.py
climaf/projects/ref_obs_cnrm.py
climaf-2.0.1.0.data/data/angle.ncl
climaf-2.0.1.0.data/data/angle_data_CNRM.nc
climaf-2.0.1.0.data/data/ml2pl
climaf-2.0.1.0.data/scripts/LinearRegression_UVCDAT.py
climaf-2.0.1.0.data/scripts/cdfsections.sh
climaf-2.0.1.0.data/scripts/cdfsectionsm.sh
climaf-2.0.1.0.dist-info/LICENSE.rst
climaf-2.0.1.0.dist-info/METADATA
climaf-2.0.1.0.dist-info/WHEEL
climaf-2.0.1.0.dist-info/top_level.txt
climaf-2.0.1.0.dist-info/RECORD
